AUTHORS.rst
CONTRIBUTING.rst
HISTORY.rst
LICENSE
MANIFEST.in
README.rst
setup.cfg
setup.py
django_coap/__init__.py
django_coap/apps.py
django_coap/models.py
django_coap/urls.py
django_coap/views.py
django_coap.egg-info/PKG-INFO
django_coap.egg-info/SOURCES.txt
django_coap.egg-info/dependency_links.txt
django_coap.egg-info/not-zip-safe
django_coap.egg-info/top_level.txt
django_coap/static/css/django_coap.css
django_coap/static/js/django_coap.js
django_coap/templates/django_coap/base.html