Metadata-Version: 1.1
Name: django-coap
Version: 0.1.0
Summary: Your project description goes here
Home-page: https://github.com/bopo/django-coap
Author: bopo.wang
Author-email: ibopo@126.com
License: MIT
Keywords: django-coap
Platform: UNKNOWN
Classifier: Development Status :: 3 - Alpha
Classifier: Framework :: Django
Classifier: Framework :: Django :: 1.10
Classifier: Intended Audience :: Developers
Classifier: License :: OSI Approved :: BSD License
Classifier: Natural Language :: English
Classifier: Programming Language :: Python :: 2
Classifier: Programming Language :: Python :: 2.7
Classifier: Programming Language :: Python :: 3
Classifier: Programming Language :: Python :: 3.4
Classifier: Programming Language :: Python :: 3.5
